mlgame/.DS_Store
mlgame/__init__.py
mlgame/__main__.py
mlgame/mlgame_obj.py
mlgame/version.py
mlgame/argument/__init__.py
mlgame/argument/cmd_argument.py
mlgame/argument/game_argument.py
mlgame/argument/model.py
mlgame/argument/tool.py
mlgame/assets/NotoSansTC-Regular.ttf
mlgame/assets/__init__.py
mlgame/assets/burnfont.otf
mlgame/assets/icon.png
mlgame/core/__init__.py
mlgame/core/communication.py
mlgame/core/env.py
mlgame/core/errno.py
mlgame/core/exceptions.py
mlgame/core/model.py
mlgame/core/process.py
mlgame/core/security.py
mlgame/crosslang/__init__.py
mlgame/crosslang/client.py
mlgame/crosslang/exceptions.py
mlgame/crosslang/ext_lang_map.py
mlgame/crosslang/main.py
mlgame/crosslang/compile/__init__.py
mlgame/crosslang/compile/cpp/__init__.py
mlgame/crosslang/compile/cpp/main.py
mlgame/executor/__init__.py
mlgame/executor/ai_client.py
mlgame/executor/az_uploader.py
mlgame/executor/displayer.py
mlgame/executor/game.py
mlgame/executor/interface.py
mlgame/executor/manual.py
mlgame/executor/recorder.py
mlgame/executor/websocket_executor.py
mlgame/game/__init__.py
mlgame/game/generic.py
mlgame/game/paia_game.py
mlgame/game/physics.py
mlgame/tests/__init__.py
mlgame/tests/env.py
mlgame/tests/test_azure_upload.py
mlgame/tests/test_cmd_argument.py
mlgame/tests/test_decorator.py
mlgame/tests/test_draw_ch_txt.py
mlgame/tests/test_game_argument.py
mlgame/tests/test_game_entity.py
mlgame/tests/test_logger.py
mlgame/tests/test_tools.py
mlgame/utils/__init__.py
mlgame/utils/azure.py
mlgame/utils/enum.py
mlgame/utils/io.py
mlgame/utils/logger.py
mlgame/utils/prof.py
mlgame/utils/recorder.py
mlgame/view/__init__.py
mlgame/view/audio_model.py
mlgame/view/decorator.py
mlgame/view/sound_controller.py
mlgame/view/view.py
mlgame/view/view_model.py
mlgame-10.7.1.dist-info/METADATA
mlgame-10.7.1.dist-info/WHEEL
mlgame-10.7.1.dist-info/top_level.txt
mlgame-10.7.1.dist-info/RECORD
