Metadata-Version: 2.4
Name: mlgame
Version: 10.7.1
Summary: A machine learning game framework based on Pygame
Home-page: https://github.com/PAIA-Playful-AI-Arena/MLGame
Author: PAIA-Tech
Author-email: service@paia-tech.com
Keywords: AI,machine learning,game,framework
Classifier: Programming Language :: Python :: 3.10
Classifier: License :: OSI Approved :: MIT License
Classifier: Operating System :: OS Independent
Requires-Python: >=3.10.0, <3.13.0
Requires-Dist: pygame<3.0,>=2.5.2
Requires-Dist: pandas==1.4.1
Requires-Dist: pydantic==2.10.3
Requires-Dist: websockets==10.2
Requires-Dist: orjson<4.0,>3.0
Requires-Dist: loguru>=0.7.2
Requires-Dist: azure-storage-blob>=12.20
Requires-Dist: pyseccomp==0.1.2
Dynamic: author
Dynamic: author-email
Dynamic: classifier
Dynamic: description
Dynamic: description-content-type
Dynamic: home-page
Dynamic: keywords
Dynamic: requires-dist
Dynamic: requires-python
Dynamic: summary
